taidy/__init__.py
taidy/__main__.py
taidy/cli.py
taidy-0.1.0.dist-info/licenses/LICENSE
taidy-0.1.0.dist-info/METADATA
taidy-0.1.0.dist-info/WHEEL
taidy-0.1.0.dist-info/entry_points.txt
taidy-0.1.0.dist-info/top_level.txt
taidy-0.1.0.dist-info/RECORD
