Metadata-Version: 2.4
Name: taidy
Version: 0.1.0
Summary: Smart linter/formatter with automatic tool detection
Author: singletoned
License-Expression: MIT
Project-URL: Homepage, https://github.com/singletoned/taidy
Project-URL: Repository, https://github.com/singletoned/taidy
Project-URL: Bug Reports, https://github.com/singletoned/taidy/issues
Project-URL: Changelog, https://github.com/singletoned/taidy/blob/main/CHANGELOG.md
Keywords: linter,formatter,python,javascript,typescript,go,rust,ruby,php,sql,shell,css,json,html,markdown
Classifier: Development Status :: 4 - Beta
Classifier: Environment :: Console
Classifier: Intended Audience :: Developers
Classifier: Operating System :: OS Independent
Classifier: Programming Language :: Python :: 3
Classifier: Programming Language :: Python :: 3.6
Classifier: Programming Language :: Python :: 3.7
Classifier: Programming Language :: Python :: 3.8
Classifier: Programming Language :: Python :: 3.9
Classifier: Programming Language :: Python :: 3.10
Classifier: Programming Language :: Python :: 3.11
Classifier: Programming Language :: Python :: 3.12
Classifier: Topic :: Software Development :: Quality Assurance
Classifier: Topic :: Software Development :: Libraries :: Python Modules
Classifier: Topic :: Utilities
Requires-Python: >=3.6
License-File: LICENSE
Provides-Extra: dev
Requires-Dist: pytest; extra == "dev"
Requires-Dist: black; extra == "dev"
Requires-Dist: ruff; extra == "dev"
Dynamic: license-file
